randify/RandomVariable.py
randify/__init__.py
randify/plot.py
randify/randify.py
randify/utils.py
randify-0.1.0.dist-info/LICENSE.md
randify-0.1.0.dist-info/METADATA
randify-0.1.0.dist-info/WHEEL
randify-0.1.0.dist-info/top_level.txt
randify-0.1.0.dist-info/RECORD
