Metadata-Version: 2.1
Name: randify
Version: 0.1.0
Summary: Simple probability density function estimation for existing code
Author-email: Jonas Nebl <jonas.nebl@tum.de>
License: The MIT License (MIT)
Keywords: montecarlo,random
Requires-Python: >=3.8
License-File: LICENSE.md
Requires-Dist: numpy
Requires-Dist: matplotlib
Requires-Dist: KDEpy
